gtrends/__init__.py
gtrends/timeline.py
gtrendspy/__init__.py
gtrendspy/timeline.py
gtrendspy/topterms.py
gtrendspy-1.0.5.dist-info/METADATA
gtrendspy-1.0.5.dist-info/WHEEL
gtrendspy-1.0.5.dist-info/top_level.txt
gtrendspy-1.0.5.dist-info/RECORD
