Metadata-Version: 2.1
Name: gtrendspy
Version: 1.0.5
Summary: Private package for pulling and merging Google Trends data
Home-page: https://github.com/tlcaputi/gtrendspy
Author: Theodore L Caputi
Author-email: tcaputi@mit.edu
License: No License
Platform: UNKNOWN
